xayax/NftMetadata.json
xayax/WCHI.json
xayax/XayaAccounts.json
xayax/XayaPolicy.json
xayax/__init__.py
xayax/core.py
xayax/eth.py
xayax/gametest.py
xayax/rpcproxy.py
xayax/testcase.py
xayax-1.4.1.dist-info/licenses/AUTHORS
xayax-1.4.1.dist-info/licenses/COPYING
xayax-1.4.1.dist-info/METADATA
xayax-1.4.1.dist-info/WHEEL
xayax-1.4.1.dist-info/top_level.txt
xayax-1.4.1.dist-info/RECORD
