Metadata-Version: 2.4
Name: xayax
Version: 1.4.1
Summary: Python framework for testing with Xaya X
Author-email: Daniel Kraft <d@domob.eu>
License: The MIT License (MIT)
Project-URL: Homepage, https://xaya.io
Project-URL: Repository, https://github.com/xaya/xayax
Classifier: Programming Language :: Python :: 3
Classifier: Operating System :: OS Independent
Classifier: License :: OSI Approved :: MIT License
Requires-Python: >=3.9
License-File: COPYING
License-File: AUTHORS
Requires-Dist: jsonrpclib-pelix
Requires-Dist: requests
Requires-Dist: web3==7
Requires-Dist: xayagametest
Dynamic: license-file
